mw_pyhelper/__init__.py
mw_pyhelper/cfgloader.py
mw_pyhelper/logcfg.py
mw_pyhelper/messaging/__init__.py
mw_pyhelper/messaging/telegrambot.py
mw_pyhelper/network/ipservice.py
mw_pyhelper/webbot/__init__.py
mw_pyhelper/webbot/constants.py
mw_pyhelper/webbot/playwright_mgr.py
mw_pyhelper/webbot/webdriver_mgr.py
mw_pyhelper/webbot/wiredriver_mgr.py
mw_pyhelper-1.0.5.dist-info/LICENSE
mw_pyhelper-1.0.5.dist-info/METADATA
mw_pyhelper-1.0.5.dist-info/WHEEL
mw_pyhelper-1.0.5.dist-info/top_level.txt
mw_pyhelper-1.0.5.dist-info/RECORD
