Metadata-Version: 2.1
Name: mw_pyhelper
Version: 1.0.5
Summary: A set of python helper classes / utilities from MicWan
Author-email: Michael Wan <hkmicmic@gmail.com>
License: MIT License
Project-URL: Homepage, https://github.com/micwan88/mw_pyhelper
Requires-Python: >=3.9
License-File: LICENSE
Requires-Dist: requests
Requires-Dist: jproperties
Requires-Dist: pyyaml
Provides-Extra: pw-bot
Requires-Dist: playwright ; extra == 'pw-bot'
Provides-Extra: webbot
Requires-Dist: selenium ; extra == 'webbot'
Provides-Extra: wirebot
Requires-Dist: selenium ; extra == 'wirebot'
Requires-Dist: selenium-wire ; extra == 'wirebot'
Requires-Dist: blinker ==1.7.0 ; extra == 'wirebot'
Requires-Dist: setuptools ; extra == 'wirebot'
Requires-Dist: cffi ; extra == 'wirebot'
